{"address1": null, "address2": "RUE DE LA SAUDRAIS", "city": "SAINT LUNAIRE", "convocationLabel": "SALLE OMNISPORTS POL LEBRETON", "distance": 0.0, "fullAddress": "RUE DE LA SAUDRAIS 35800 SAINT LUNAIRE", "giveBlood": 1, "givePlasma": 0, "givePlatelet": 0, "regionCode": "016", "groupCode": "F70234", "latitude": 48.629694, "longitude": -2.110176, "name": "ST LUNAIRE GYMNASE SEMAINE", "postCode": "35800", "samplingLocationCode": "2", "horaires": null, "infos": null, "metro": null, "bus": null, "tram": null, "parking": null, "debutInfos": null, "finInfos": null, "ville": null, "id": null, "phone": null, "urlBlood": null, "urlPlasma": null, "urlPlatelets": null}
{"address1": null, "address2": "109 RUE DES ECOLES", "city": "SAINT LUNAIRE", "convocationLabel": "SALLE AIME LE FOLL - RUE DES ECOLES", "distance": 0.0, "fullAddress": "109 RUE DES ECOLES 35800 SAINT LUNAIRE", "giveBlood": 1, "givePlasma": 0, "givePlatelet": 0, "regionCode": "016", "groupCode": "F70234", "latitude": 48.632547, "longitude": -2.107033, "name": "ST LUNAIRE LE FOLL SEMAINE", "postCode": "35800", "samplingLocationCode": "246", "horaires": null, "infos": null, "metro": null, "bus": null, "tram": null, "parking": null, "debutInfos": null, "finInfos": null, "ville": null, "id": null, "phone": null, "urlBlood": null, "urlPlasma": null, "urlPlatelets": null}
