{"address1": "MSA", "address2": "12 rue de Paimpont", "city": "ST-BRIEUC", "convocationLabel": "SALLES 441 A 444", "distance": 0.0, "fullAddress": "MSA 12 rue de Paimpont 22000 ST-BRIEUC", "giveBlood": 1, "givePlasma": 0, "givePlatelet": 0, "regionCode": "016", "groupCode": "F10209", "latitude": 48.52189, "longitude": -2.788905, "name": "Salles 441\u00e0 444", "postCode": "22000", "samplingLocationCode": "1330", "horaires": null, "infos": null, "metro": null, "bus": null, "tram": null, "parking": null, "debutInfos": null, "finInfos": null, "ville": null, "id": null, "phone": null, "urlBlood": null, "urlPlasma": null, "urlPlatelets": null}
