{"address1": null, "address2": "RUE DU GENERAL DE GAULLE", "city": "MINIAC MORVAN", "convocationLabel": "L'ESPACE BEL AIR SALLE 1 ET 2", "distance": 0.0, "fullAddress": "RUE DU GENERAL DE GAULLE 35540 MINIAC MORVAN", "giveBlood": 1, "givePlasma": 0, "givePlatelet": 0, "regionCode": "016", "groupCode": "F35124", "latitude": 48.514389, "longitude": -1.903921, "name": "MINIAC-MORVAN SEMAINE", "postCode": "35540", "samplingLocationCode": "1", "horaires": null, "infos": null, "metro": null, "bus": null, "tram": null, "parking": null, "debutInfos": null, "finInfos": null, "ville": null, "id": null, "phone": null, "urlBlood": null, "urlPlasma": null, "urlPlatelets": null}
{"address1": "SALLE 1 ET 2", "address2": "RUE DU GENERAL DE GAULLE", "city": "MINIAC MORVAN", "convocationLabel": "L'ESPACE BEL AIR", "distance": 0.0, "fullAddress": "SALLE 1 ET 2 RUE DU GENERAL DE GAULLE 35540 MINIAC MORVAN", "giveBlood": 1, "givePlasma": 0, "givePlatelet": 0, "regionCode": "016", "groupCode": "F35124", "latitude": 48.51458359, "longitude": -1.90387416, "name": "2 MINIAC-MORVAN-BEL AIR AM ", "postCode": "35540", "samplingLocationCode": "2", "horaires": null, "infos": null, "metro": null, "bus": null, "tram": null, "parking": null, "debutInfos": null, "finInfos": null, "ville": null, "id": null, "phone": null, "urlBlood": null, "urlPlasma": null, "urlPlatelets": null}
{"address1": "SALLE 1 ET 2", "address2": "RUE DU GENERAL DE GAULLE", "city": "MINIAC MORVAN", "convocationLabel": "L'ESPACE BEL AIR", "distance": 0.0, "fullAddress": "SALLE 1 ET 2 RUE DU GENERAL DE GAULLE 35540 MINIAC MORVAN", "giveBlood": 1, "givePlasma": 0, "givePlatelet": 0, "regionCode": "016", "groupCode": "F35124", "latitude": 48.514389, "longitude": -1.903921, "name": "2 MINIAC-MORVAN-BEL AIR DAM", "postCode": "35540", "samplingLocationCode": "3", "horaires": null, "infos": null, "metro": null, "bus": null, "tram": null, "parking": null, "debutInfos": null, "finInfos": null, "ville": null, "id": null, "phone": null, "urlBlood": null, "urlPlasma": null, "urlPlatelets": null}
{"address1": "SALLE 1 ET 2", "address2": "RUE DU GENERAL DE GAULLE", "city": "MINIAC MORVAN", "convocationLabel": "L'ESPACE BEL AIR", "distance": 0.0, "fullAddress": "SALLE 1 ET 2 RUE DU GENERAL DE GAULLE 35540 MINIAC MORVAN", "giveBlood": 1, "givePlasma": 0, "givePlatelet": 0, "regionCode": "016", "groupCode": "F35124", "latitude": 48.514458, "longitude": -1.903921, "name": "2 MINIAC-MORVAN-BEL AIR MAT", "postCode": "35540", "samplingLocationCode": "4", "horaires": null, "infos": null, "metro": null, "bus": null, "tram": null, "parking": null, "debutInfos": null, "finInfos": null, "ville": null, "id": null, "phone": null, "urlBlood": null, "urlPlasma": null, "urlPlatelets": null}
