{"address1": null, "address2": null, "city": "LARMOR PLAGE", "convocationLabel": "LES RIVES DU TER", "distance": 0.0, "fullAddress": "56260 LARMOR PLAGE", "giveBlood": 1, "givePlasma": 0, "givePlatelet": 0, "regionCode": "016", "groupCode": "F30257", "latitude": 47.716003, "longitude": -3.39156, "name": "LARMOR-H\u00f4tel Best Western", "postCode": "56260", "samplingLocationCode": "1", "horaires": null, "infos": null, "metro": null, "bus": null, "tram": null, "parking": null, "debutInfos": null, "finInfos": null, "ville": null, "id": null, "phone": null, "urlBlood": null, "urlPlasma": null, "urlPlatelets": null}
{"address1": "HOTEL BEST WESTERN-LES RIVES DU TER", "address2": null, "city": "LARMOR PLAGE", "convocationLabel": "LES RIVES DU TER", "distance": 0.0, "fullAddress": "HOTEL BEST WESTERN-LES RIVES DU TER 56260 LARMOR PLAGE", "giveBlood": 1, "givePlasma": 0, "givePlatelet": 0, "regionCode": "016", "groupCode": "F30257", "latitude": 47.71949, "longitude": -3.375857, "name": "LARMOR-H\u00f4tel Best Western AM", "postCode": "56260", "samplingLocationCode": "2", "horaires": null, "infos": null, "metro": null, "bus": null, "tram": null, "parking": null, "debutInfos": null, "finInfos": null, "ville": null, "id": null, "phone": null, "urlBlood": null, "urlPlasma": null, "urlPlatelets": null}
