{"address1": null, "address2": "TALHOUET", "city": "PLUVIGNER", "convocationLabel": "ENTREPRISE HILL ROM", "distance": 0.0, "fullAddress": "TALHOUET 56330 PLUVIGNER", "giveBlood": 1, "givePlasma": 0, "givePlatelet": 0, "regionCode": "016", "groupCode": "F30176", "latitude": 47.753351, "longitude": -3.025917, "name": "HILL ROM (VANNES)", "postCode": "56330", "samplingLocationCode": "1512", "horaires": null, "infos": null, "metro": null, "bus": null, "tram": null, "parking": null, "debutInfos": null, "finInfos": null, "ville": null, "id": null, "phone": null, "urlBlood": null, "urlPlasma": null, "urlPlatelets": null}
{"address1": null, "address2": "TALHOUET", "city": "PLUVIGNER", "convocationLabel": "ENTREPRISE HILL ROM", "distance": 0.0, "fullAddress": "TALHOUET 56330 PLUVIGNER", "giveBlood": 1, "givePlasma": 0, "givePlatelet": 0, "regionCode": "016", "groupCode": "F30176", "latitude": 47.753351, "longitude": -3.025917, "name": "HILL ROM (LORIENT)", "postCode": "56330", "samplingLocationCode": "2", "horaires": null, "infos": null, "metro": null, "bus": null, "tram": null, "parking": null, "debutInfos": null, "finInfos": null, "ville": null, "id": null, "phone": null, "urlBlood": null, "urlPlasma": null, "urlPlatelets": null}
{"address1": "HILL ROM", "address2": "TALHOUET", "city": "PLUVIGNER", "convocationLabel": "ENTREPRISE HILL ROM", "distance": 0.0, "fullAddress": "HILL ROM TALHOUET 56330 PLUVIGNER", "giveBlood": 1, "givePlasma": 0, "givePlatelet": 0, "regionCode": "016", "groupCode": "F30176", "latitude": 47.753351, "longitude": -3.025917, "name": "HILL ROM (VANNES M)", "postCode": "56330", "samplingLocationCode": "3", "horaires": null, "infos": null, "metro": null, "bus": null, "tram": null, "parking": null, "debutInfos": null, "finInfos": null, "ville": null, "id": null, "phone": null, "urlBlood": null, "urlPlasma": null, "urlPlatelets": null}
