{"address1": "LYCEE ST JOSEPH LA SALLE", "address2": "39 BOULEVARD DES ILES", "city": "VANNES", "convocationLabel": "BAT B SALLE DS  Inscrivez vous aupr\u00e8s du  CPE", "distance": 0.0, "fullAddress": "LYCEE ST JOSEPH LA SALLE 39 BOULEVARD DES ILES 56000 VANNES", "giveBlood": 1, "givePlasma": 0, "givePlatelet": 0, "regionCode": "016", "groupCode": "F30313", "latitude": 47.653816, "longitude": -2.780039, "name": "VANNES LYCEE ST JOSEPH", "postCode": "56000", "samplingLocationCode": "1410", "horaires": null, "infos": null, "metro": null, "bus": null, "tram": null, "parking": null, "debutInfos": null, "finInfos": null, "ville": null, "id": null, "phone": null, "urlBlood": null, "urlPlasma": null, "urlPlatelets": null}
{"address1": "LYCEE ST JOSEPH LA SALLE", "address2": "39 BOULEVARD DES ILES", "city": "VANNES", "convocationLabel": "BAT D PERMANENCES  Inscrivez vous \u00e0 la Vie Scolair", "distance": 0.0, "fullAddress": "LYCEE ST JOSEPH LA SALLE 39 BOULEVARD DES ILES 56000 VANNES", "giveBlood": 1, "givePlasma": 0, "givePlatelet": 0, "regionCode": "016", "groupCode": "F30313", "latitude": 47.653816, "longitude": -2.780039, "name": "VANNES-LYCEE ST JOSEPH LASALLE", "postCode": "56000", "samplingLocationCode": "2", "horaires": null, "infos": null, "metro": null, "bus": null, "tram": null, "parking": null, "debutInfos": null, "finInfos": null, "ville": null, "id": null, "phone": null, "urlBlood": null, "urlPlasma": null, "urlPlatelets": null}
{"address1": "LYCEE ST JOSEPH LASALLE", "address2": "39 BOULEVARD DES ILES", "city": "VANNES", "convocationLabel": "BAT D PERMANENCES Inscrivez vous aupr\u00e8s du CPE", "distance": 0.0, "fullAddress": "LYCEE ST JOSEPH LASALLE 39 BOULEVARD DES ILES 56000 VANNES", "giveBlood": 1, "givePlasma": 0, "givePlatelet": 0, "regionCode": "016", "groupCode": "F30313", "latitude": 47.653816, "longitude": -2.780039, "name": "V ST JO LASALLE 08h30 12h30", "postCode": "56000", "samplingLocationCode": "3", "horaires": null, "infos": null, "metro": null, "bus": null, "tram": null, "parking": null, "debutInfos": null, "finInfos": null, "ville": null, "id": null, "phone": null, "urlBlood": null, "urlPlasma": null, "urlPlatelets": null}
