{"address1": null, "address2": "PLACE DE LA  FORGE", "city": "ST GREGOIRE", "convocationLabel": "CENTRE ANIMATION LA FORGE6 (pr\u00e8s du centre co)", "distance": 0.0, "fullAddress": "PLACE DE LA  FORGE 35760 ST GREGOIRE", "giveBlood": 1, "givePlasma": 0, "givePlatelet": 0, "regionCode": "016", "groupCode": "F70226", "latitude": 48.151433, "longitude": -1.687928, "name": "ST GREGOIRE", "postCode": "35760", "samplingLocationCode": "238", "horaires": null, "infos": null, "metro": null, "bus": null, "tram": null, "parking": null, "debutInfos": null, "finInfos": null, "ville": null, "id": null, "phone": null, "urlBlood": null, "urlPlasma": null, "urlPlatelets": null}
