{"address1": null, "address2": "3 CITE DES FLEURS", "city": "PEILLAC", "convocationLabel": "SALLE POLYVALENTE", "distance": 0.0, "fullAddress": "3 CITE DES FLEURS 56220 PEILLAC", "giveBlood": 1, "givePlasma": 0, "givePlatelet": 0, "regionCode": "016", "groupCode": "F30336", "latitude": 48.03528, "longitude": -3.484789, "name": "PEILLAC (M)", "postCode": "56220", "samplingLocationCode": "1564", "horaires": null, "infos": null, "metro": null, "bus": null, "tram": null, "parking": null, "debutInfos": null, "finInfos": null, "ville": null, "id": null, "phone": null, "urlBlood": null, "urlPlasma": null, "urlPlatelets": null}
{"address1": null, "address2": "3 CITE DES FLEURS", "city": "PEILLAC", "convocationLabel": "SALLE POLYVALENTE", "distance": 0.0, "fullAddress": "3 CITE DES FLEURS 56220 PEILLAC", "giveBlood": 1, "givePlasma": 0, "givePlatelet": 0, "regionCode": "016", "groupCode": "F30336", "latitude": 48.03528, "longitude": -3.484789, "name": "PEILLAC (S)", "postCode": "56220", "samplingLocationCode": "2", "horaires": null, "infos": null, "metro": null, "bus": null, "tram": null, "parking": null, "debutInfos": null, "finInfos": null, "ville": null, "id": null, "phone": null, "urlBlood": null, "urlPlasma": null, "urlPlatelets": null}
{"address1": null, "address2": "3 CITES DES FLEURS", "city": "PEILLAC", "convocationLabel": "SALLE POLYVALENTE", "distance": 0.0, "fullAddress": "3 CITES DES FLEURS 56220 PEILLAC", "giveBlood": 1, "givePlasma": 0, "givePlatelet": 0, "regionCode": "016", "groupCode": "F30336", "latitude": 47.71421051, "longitude": -2.21977401, "name": "PEILLAC 14 H-18H", "postCode": "56220", "samplingLocationCode": "3", "horaires": null, "infos": null, "metro": null, "bus": null, "tram": null, "parking": null, "debutInfos": null, "finInfos": null, "ville": null, "id": null, "phone": null, "urlBlood": null, "urlPlasma": null, "urlPlatelets": null}
