{"address1": "2 rue Henri Dunant", "address2": "2 rue Henri Dunant", "city": "PAIMPOL", "convocationLabel": "Salle Centre Dunant n\u00b01", "distance": 0.0, "fullAddress": "2 rue Henri Dunant 2 rue Henri Dunant 22500 PAIMPOL", "giveBlood": 1, "givePlasma": 0, "givePlatelet": 0, "regionCode": "016", "groupCode": "F18004", "latitude": 48.781033, "longitude": -3.049788, "name": "Salle Centre Dunant n\u00b01", "postCode": "22500", "samplingLocationCode": "3", "horaires": null, "infos": null, "metro": null, "bus": null, "tram": null, "parking": null, "debutInfos": null, "finInfos": null, "ville": null, "id": null, "phone": null, "urlBlood": null, "urlPlasma": null, "urlPlatelets": null}
{"address1": null, "address2": "Chemin de LANDOUEZEC/Bourg", "city": "PLOUNEZ", "convocationLabel": "SALLE DES FETES DE PLOUNEZ", "distance": 0.0, "fullAddress": "Chemin de LANDOUEZEC/Bourg 22500 PLOUNEZ", "giveBlood": 1, "givePlasma": 0, "givePlatelet": 0, "regionCode": "016", "groupCode": "F18004", "latitude": 48.765977, "longitude": -3.086361, "name": "PLOUNEZ SDF", "postCode": "22500", "samplingLocationCode": "4", "horaires": null, "infos": null, "metro": null, "bus": null, "tram": null, "parking": null, "debutInfos": null, "finInfos": null, "ville": null, "id": null, "phone": null, "urlBlood": null, "urlPlasma": null, "urlPlatelets": null}
{"address1": null, "address2": "Chemin de LANDOUEZEC/Bourg", "city": "PLOUNEZ", "convocationLabel": "Salle des F\u00eates PLOUNEZ", "distance": 0.0, "fullAddress": "Chemin de LANDOUEZEC/Bourg 22500 PLOUNEZ", "giveBlood": 1, "givePlasma": 0, "givePlatelet": 0, "regionCode": "016", "groupCode": "F18004", "latitude": 48.765977, "longitude": -3.086361, "name": "Salle des F\u00eates PLOUNEZ", "postCode": "22500", "samplingLocationCode": "6", "horaires": null, "infos": null, "metro": null, "bus": null, "tram": null, "parking": null, "debutInfos": null, "finInfos": null, "ville": null, "id": null, "phone": null, "urlBlood": null, "urlPlasma": null, "urlPlatelets": null}
