{"address1": "INTERNAT", "address2": "RUE DE KERICHEN", "city": "BREST", "convocationLabel": "LYCEE VAUBAN", "distance": 0.0, "fullAddress": "INTERNAT RUE DE KERICHEN 29200 BREST", "giveBlood": 1, "givePlasma": 0, "givePlatelet": 0, "regionCode": "016", "groupCode": "F50170", "latitude": 48.407011, "longitude": -4.481064, "name": "LYCEE VAUBAN J2", "postCode": "29200", "samplingLocationCode": "2", "horaires": null, "infos": null, "metro": null, "bus": null, "tram": null, "parking": null, "debutInfos": null, "finInfos": null, "ville": null, "id": null, "phone": null, "urlBlood": null, "urlPlasma": null, "urlPlatelets": null}
{"address1": "INTERNAT", "address2": "RUE DE KERICHEN", "city": "BREST", "convocationLabel": "LYCEE VAUBAN", "distance": 0.0, "fullAddress": "INTERNAT RUE DE KERICHEN 29200 BREST", "giveBlood": 1, "givePlasma": 0, "givePlatelet": 0, "regionCode": "016", "groupCode": "F50170", "latitude": 48.407011, "longitude": -4.481064, "name": "LYCEE VAUBAN J1", "postCode": "29200", "samplingLocationCode": "750", "horaires": null, "infos": null, "metro": null, "bus": null, "tram": null, "parking": null, "debutInfos": null, "finInfos": null, "ville": null, "id": null, "phone": null, "urlBlood": null, "urlPlasma": null, "urlPlatelets": null}
