{"address1": "LYCEE TECHNOLOGIQUE PRIVE STE THERESE", "address2": "27 RUE SULLY PRUDHOMME", "city": "RENNES", "convocationLabel": "SALLE DE CONFERENCES", "distance": 0.0, "fullAddress": "LYCEE TECHNOLOGIQUE PRIVE STE THERESE 27 RUE SULLY PRUDHOMME 35200 RENNES", "giveBlood": 1, "givePlasma": 0, "givePlatelet": 0, "regionCode": "016", "groupCode": "F70371", "latitude": 48.094872, "longitude": -1.666893, "name": "LYCEE TECH. PRIVE STE THERESE", "postCode": "35200", "samplingLocationCode": "397", "horaires": null, "infos": null, "metro": null, "bus": null, "tram": null, "parking": null, "debutInfos": null, "finInfos": null, "ville": null, "id": null, "phone": null, "urlBlood": null, "urlPlasma": null, "urlPlatelets": null}
